pytaoassets
